setup.py
rpc_gateway/__init__.py
rpc_gateway/__version__.py
rpc_gateway/client.py
rpc_gateway/errors.py
rpc_gateway/gateway.py
rpc_gateway/http_gateway.py
rpc_gateway/messages_pb2.py
rpc_gateway/registry.py
rpc_gateway/server.py
rpc_gateway/utils.py
rpc_gateway/websocket_connection.py
rpc_gateway.egg-info/PKG-INFO
rpc_gateway.egg-info/SOURCES.txt
rpc_gateway.egg-info/dependency_links.txt
rpc_gateway.egg-info/requires.txt
rpc_gateway.egg-info/top_level.txt