Metadata-Version: 2.1
Name: rpc-gateway
Version: 0.5.1
Summary: RPC client, server and gateway that allows remote control of Python objects
Home-page: https://gitlab.com/heingroup/rpc_gateway
Author: Sean Clark
Author-email: sean@v13inc.com
License: MIT
Platform: UNKNOWN
Requires-Python: >=3.6.0
